autologging.py
Autologging-1.3.2.dist-info/METADATA
Autologging-1.3.2.dist-info/RECORD
Autologging-1.3.2.dist-info/WHEEL
Autologging-1.3.2.dist-info/top_level.txt
